{
"currentCoin":{"crCoinY":"cc BTC", "crTextY":"BTC", "crCoinG":"cc XRP", "crTextG":"XRP"},

"Coins":[{"Coin":"cc BTC","Texts":"BTC","Alt":"Bitcoin","_Id":1},
         {"Coin":"cc ETH","Texts":"ETH","Alt":"Etherium","_Id":2},
         {"Coin":"cc LTC","Texts":"LTC","Alt":"Litecoin","_Id":3},
         {"Coin":"cc XMR","Texts":"XMR","Alt":"Monero","_Id":4},
         {"Coin":"cc XRP","Texts":"XRP","Alt":"Ripple","_Id":5}],


"currentFlag" :{"crFlag": "flag-icon flag-icon-us","crText": "ENGLISH"},

"languages":[{"Texts":"FRENCH","Flag":"flag-icon flag-icon-fr","alt":"French flag"},
             {"Texts":"SPANISH","Flag":"flag-icon flag-icon-es","alt":"Spanish flag"},
             {"Texts":"ENGLISH","Flag":"flag-icon flag-icon-us","alt":"English flag"}]
}
